docstringify/__init__.py
docstringify/__main__.py
docstringify/cli.py
docstringify/components.py
docstringify/exceptions.py
docstringify/converters/__init__.py
docstringify/converters/base.py
docstringify/converters/google.py
docstringify/converters/numpydoc.py
docstringify/converters/stub.py
docstringify/nodes/__init__.py
docstringify/nodes/base.py
docstringify/nodes/function.py
docstringify/traversal/__init__.py
docstringify/traversal/transformer.py
docstringify/traversal/visitor.py
docstringify-1.1.1.dist-info/METADATA
docstringify-1.1.1.dist-info/WHEEL
docstringify-1.1.1.dist-info/entry_points.txt
docstringify-1.1.1.dist-info/licenses/LICENSE
docstringify-1.1.1.dist-info/RECORD
