Metadata-Version: 2.4
Name: docstringify
Version: 1.1.1
Summary: Flag missing docstrings and, optionally, generate them from signatures and type annotations.
Project-URL: Documentation, https://github.com/stefmolin/docstringify
Project-URL: Homepage, https://github.com/stefmolin/docstringify
Project-URL: Source, https://github.com/stefmolin/docstringify
Author-email: Stefanie Molin <docstringify@stefaniemolin.com>
License-Expression: MIT
License-File: LICENSE
Keywords: ast,docstring generation,google-style docstring,numpydoc-style docstring,pre-commit
Classifier: Development Status :: 4 - Beta
Classifier: Programming Language :: Python
Classifier: Programming Language :: Python :: 3 :: Only
Classifier: Programming Language :: Python :: 3.9
Classifier: Programming Language :: Python :: 3.10
Classifier: Programming Language :: Python :: 3.11
Classifier: Programming Language :: Python :: 3.12
Classifier: Programming Language :: Python :: 3.13
Requires-Python: >=3.9
